mavera/__init__.py
mavera/client.py
mavera/database.py
mavera/exceptions.py
mavera/models.py
mavera/query_processor.py
mavera-0.1.5.dist-info/METADATA
mavera-0.1.5.dist-info/WHEEL
mavera-0.1.5.dist-info/top_level.txt
mavera-0.1.5.dist-info/RECORD
