Metadata-Version: 2.2
Name: mavera
Version: 0.1.5
Summary: Python SDK for interacting with the Mavera API
Home-page: https://github.com/LubedB1nary/mavera
Author: Alex Hassan
Author-email: your.email@example.com
Classifier: Programming Language :: Python :: 3
Classifier: Operating System :: OS Independent
Requires-Python: >=3.6
Requires-Dist: httpx>=0.18.0
Dynamic: author
Dynamic: author-email
Dynamic: classifier
Dynamic: home-page
Dynamic: requires-dist
Dynamic: requires-python
Dynamic: summary
